README.md
setup.py
pyramid_settings_wrapper/__init__.py
pyramid_settings_wrapper/version.py
pyramid_settings_wrapper.egg-info/PKG-INFO
pyramid_settings_wrapper.egg-info/SOURCES.txt
pyramid_settings_wrapper.egg-info/dependency_links.txt
pyramid_settings_wrapper.egg-info/requires.txt
pyramid_settings_wrapper.egg-info/top_level.txt
tests/__init__.py