Metadata-Version: 1.1
Name: pyramid-settings-wrapper
Version: 0.0.3
Summary: Transforms Pyramid config into a flexible class for easy access to config values.
Home-page: https://github.com/mrichar1/pyramid_settings_wrapper
Author: Matthew Richardson
Author-email: m.richardson@ed.ac.uk
License: GNU Affero General Public License v3 or later (AGPLv3+)
Keywords: pyramid,config
Platform: UNKNOWN
Classifier: Development Status :: 5 - Production/Stable
Classifier: Framework :: Pyramid
Classifier: Intended Audience :: Developers
Classifier: License :: OSI Approved :: GNU Affero General Public License v3 or later (AGPLv3+)
Classifier: Programming Language :: Python :: 3
Classifier: Programming Language :: Python :: 3.4
Classifier: Programming Language :: Python :: 3.5
Classifier: Programming Language :: Python :: 3.6
Classifier: Topic :: Internet :: WWW/HTTP
Classifier: Topic :: Internet :: WWW/HTTP :: Dynamic Content
Classifier: Topic :: Software Development :: Libraries :: Application Frameworks
Classifier: Topic :: Software Development :: Libraries :: Python Modules
